ATHENApt/__init__.py
ATHENApt/athena_read.py
ATHENApt/plot_slice.py
ATHENApt-0.0.6.dist-info/LICENSE
ATHENApt-0.0.6.dist-info/METADATA
ATHENApt-0.0.6.dist-info/WHEEL
ATHENApt-0.0.6.dist-info/top_level.txt
ATHENApt-0.0.6.dist-info/RECORD
