Metadata-Version: 2.1
Name: ATHENApt
Version: 0.0.6
Summary: This is a complementary Python package for ATHENA++ visualization inspred by ATHENA++ plotting scripts. More test examples and .athdf files for test, please visit package Home-page.
Home-page: https://github.com/0RuiqiYang0/ATHENApt
Author: Ruiqi Yang, Xiaoyuan Yang, Ruining Zhao
License: GPL-3.0
Project-URL: Homepage, https://github.com/0RuiqiYang0/ATHENApt
Requires-Python: >=3.6
License-File: LICENSE
Requires-Dist: numpy
Requires-Dist: matplotlib
